MANIFEST.in
requirements.txt
setup.cfg
setup.py
src/persistent_celery_beat_scheduler.egg-info/PKG-INFO
src/persistent_celery_beat_scheduler.egg-info/SOURCES.txt
src/persistent_celery_beat_scheduler.egg-info/dependency_links.txt
src/persistent_celery_beat_scheduler.egg-info/not-zip-safe
src/persistent_celery_beat_scheduler.egg-info/requires.txt
src/persistent_celery_beat_scheduler.egg-info/top_level.txt
src/persistent_scheduler/__init__.py
src/persistent_scheduler/scheduler.py