Metadata-Version: 1.1
Name: persistent-celery-beat-scheduler
Version: 0.1.0
Summary: Celery Beat Scheduler that stores the scheduler data in Redis.
Home-page: UNKNOWN
Author: Richard O'Dwyer
Author-email: richard@richard.do
License: Apache 2
Platform: UNKNOWN
Classifier: Intended Audience :: Developers
Classifier: Operating System :: OS Independent
Classifier: Programming Language :: Python
Classifier: Programming Language :: Python :: 3
Classifier: Programming Language :: Python :: 3.2
Classifier: Programming Language :: Python :: 3.3
Classifier: Programming Language :: Python :: 3.4
Classifier: Programming Language :: Python :: 3.5
Classifier: Programming Language :: Python :: 3.6
Classifier: Topic :: Internet :: WWW/HTTP
